IQGO_module/BaseIQGO.py
IQGO_module/__init__.py
IQGO_module/iqgo_optimize_module.py
IQGO_module/iqgo_training.py
IQGO_module-0.1.1.dist-info/LICENSE
IQGO_module-0.1.1.dist-info/METADATA
IQGO_module-0.1.1.dist-info/WHEEL
IQGO_module-0.1.1.dist-info/top_level.txt
IQGO_module-0.1.1.dist-info/RECORD
