Metadata-Version: 2.1
Name: IQGO_module
Version: 0.1.1
Summary: IQGO: Iterative Quantum Gate Optimiser
Home-page: https://github.com/copyright2010/IQGO-Iterative-Quantum-Gate-Optimiser
Author: Tautvydas Lisas
Author-email: Tautvydas Lisas <D17125255@mytudublin.ie>
Project-URL: Homepage, https://github.com/copyright2010/IQGO-Iterative-Quantum-Gate-Optimiser
Project-URL: Issues, https://github.com/copyright2010/IQGO-Iterative-Quantum-Gate-Optimiser
Classifier: Programming Language :: Python :: 3
Classifier: License :: OSI Approved :: MIT License
Classifier: Operating System :: OS Independent
Requires-Python: >=3.6
License-File: LICENSE
